docs/.DS_Store
docs/authentication.rst
docs/changelog.rst
docs/conf.py
docs/contributing.rst
docs/fetching_secrets.rst
docs/genindex.rst
docs/index.rst
docs/install.rst
docs/overview.rst
docs/requirements.txt
docs/setting_databricks_connect.rst
docs/_templates/autosummary/base.rst
docs/_templates/autosummary/class.rst
docs/_templates/autosummary/function.rst
docs/api-src/pfore_cloud_utilities.rst
pfore_cloud_utilities/__init__.py
pfore_cloud_utilities/__pycache__/__init__.cpython-39.pyc
pfore_cloud_utilities/core/__init__.py
pfore_cloud_utilities/core/azure_aad_token_generator.py
pfore_cloud_utilities/core/azure_blob_connector.py
pfore_cloud_utilities/core/databricks_workspace.py
pfore_cloud_utilities/core/define.py
pfore_cloud_utilities/core/singleton.py
pfore_cloud_utilities/core/__pycache__/__init__.cpython-39.pyc
pfore_cloud_utilities/core/__pycache__/azure_aad_token_generator.cpython-39.pyc
pfore_cloud_utilities/core/__pycache__/azure_blob_connector.cpython-39.pyc
pfore_cloud_utilities/core/__pycache__/databricks_workspace.cpython-39.pyc
pfore_cloud_utilities/core/__pycache__/define.cpython-39.pyc
pfore_cloud_utilities/core/__pycache__/singleton.cpython-39.pyc
test/test_imports.py
pfore_cloud_utilities-0.0.0.dev6.dist-info/METADATA
pfore_cloud_utilities-0.0.0.dev6.dist-info/WHEEL
pfore_cloud_utilities-0.0.0.dev6.dist-info/top_level.txt
pfore_cloud_utilities-0.0.0.dev6.dist-info/RECORD
