Metadata-Version: 2.1
Name: pfore-cloud-utilities
Version: 0.0.0.dev6
Summary: Provides utility functions for cloud-based workflows.
Author: BahaEddine Abrougui
Author-email: bahaeddine.abrougui@lidl.com
Project-URL: repository, https://github.com/Bahaabrougui/pfore-cloud-utilities/
Project-URL: documentation, https://bahaabrougui.github.io/pfore-cloud-utilities/index.html/
Keywords: databricks,azure,mlops
Classifier: Development Status :: 3 - Alpha
Classifier: Intended Audience :: Science/Research
Classifier: Intended Audience :: Developers
Classifier: Operating System :: OS Independent
Classifier: Programming Language :: Python
Classifier: Programming Language :: Python :: 3
Classifier: Programming Language :: Python :: 3.9
Classifier: Programming Language :: Python :: 3.10
Classifier: Programming Language :: Python :: 3.11
Requires-Python: >=3.9
Requires-Dist: databricks-sdk <1.0.0,>=0.9.0
Requires-Dist: azure-identity <1.15.0,>=1.14.0
Requires-Dist: azure-storage-blob <12.19.0,>=12.18.2
